{
  "$schema": "https://ui.shadcn.com/schema/registry-item.json",
  "name": "chart",
  "type": "registry:ui",
  "registryDependencies": [],
  "dependencies": ["framer-motion", "recharts"],
  "devDependencies": [],
  "files": [
    {
      "path": "chart.tsx",
      "content": "\"use client\";\n\nimport { motion } from \"framer-motion\";\nimport { ChevronDown } from \"lucide-react\";\nimport { useEffect, useState } from \"react\";\nimport type { TooltipProps } from \"recharts\";\nimport {\n  Area,\n  AreaChart,\n  Bar,\n  BarChart,\n  CartesianGrid,\n  Line,\n  LineChart,\n  ResponsiveContainer,\n  Tooltip,\n  XAxis,\n  YAxis,\n} from \"recharts\";\nimport { cn } from \"@/lib/utils\";\n\n/** Chart colors defined in component; no CSS variables in global.css required. */\nconst CHART_PRIMARY = \"hsl(221, 83%, 53%)\";\nconst CHART_SECONDARY = \"hsl(262, 83%, 58%)\";\n\nexport type ChartType = \"bar\" | \"line\" | \"area\";\n\n/** Data item for the chart. Requires `name` (x-axis), `value` (primary series), and `secondary` (secondary series). */\nexport interface ChartDataItem {\n  name: string;\n  value: number;\n  secondary: number;\n}\n\nexport interface AnimatedChartProps {\n  /** Chart data: array of { name, value, secondary }. */\n  items: ChartDataItem[];\n  title?: string;\n  description?: string;\n  className?: string;\n  /** Controlled variant; omit to use internal state. */\n  variant?: ChartType;\n  /** Called when user changes variant (e.g. via select). */\n  onVariantChange?: (variant: ChartType) => void;\n}\n\nconst CHART_TYPE_OPTIONS: { type: ChartType; label: string }[] = [\n  { type: \"bar\", label: \"Bar\" },\n  { type: \"line\", label: \"Line\" },\n  { type: \"area\", label: \"Area\" },\n];\n\nfunction ChartTooltip({\n  active,\n  payload,\n  label,\n}: TooltipProps<number, string>) {\n  if (!(active && payload?.length)) return null;\n  return (\n    <div className=\"rounded-lg border border-border bg-popover px-3 py-2 text-popover-foreground text-xs shadow-md\">\n      <p className=\"mb-1 font-medium\">{label}</p>\n      {payload.map((entry: { color?: string; value?: number }, i: number) => (\n        <p className=\"text-muted-foreground\" key={i}>\n          <span\n            className=\"mr-1.5 inline-block h-2 w-2 rounded-full\"\n            style={{ backgroundColor: entry.color }}\n          />\n          {Number(entry.value).toLocaleString()}\n        </p>\n      ))}\n    </div>\n  );\n}\n\nexport function AnimatedChart({\n  items,\n  title = \"Analytics Overview\",\n  description = \"Monthly performance metrics\",\n  className,\n  variant: controlledVariant,\n  onVariantChange,\n}: AnimatedChartProps) {\n  const [internalVariant, setInternalVariant] = useState<ChartType>(\"bar\");\n  const [isDark, setIsDark] = useState(false);\n  const activeChart = controlledVariant ?? internalVariant;\n  const setActiveChart = (v: ChartType) => {\n    if (controlledVariant === undefined) setInternalVariant(v);\n    onVariantChange?.(v);\n  };\n\n  useEffect(() => {\n    const el = document.documentElement;\n    const check = () => setIsDark(el.classList.contains(\"dark\"));\n    check();\n    const obs = new MutationObserver(check);\n    obs.observe(el, { attributes: true, attributeFilter: [\"class\"] });\n    return () => obs.disconnect();\n  }, []);\n\n  const primaryColor = CHART_PRIMARY;\n  const secondaryColor = CHART_SECONDARY;\n  const gridColor = \"hsl(var(--border))\";\n  const textColor = isDark ? \"white\" : \"hsl(var(--foreground))\";\n\n  const commonProps = {\n    data: items,\n    margin: { top: 8, right: 8, left: -16, bottom: 0 },\n  };\n  const axisProps = {\n    stroke: \"none\",\n    tick: { fill: textColor, fontSize: 11 },\n    tickLine: false,\n  };\n\n  const renderChart = () => {\n    switch (activeChart) {\n      case \"bar\":\n        return (\n          <BarChart {...commonProps}>\n            <CartesianGrid\n              stroke={gridColor}\n              strokeDasharray=\"3 3\"\n              vertical={false}\n            />\n            <XAxis dataKey=\"name\" {...axisProps} />\n            <YAxis {...axisProps} />\n            <Tooltip content={<ChartTooltip />} />\n            <Bar\n              animationDuration={800}\n              dataKey=\"value\"\n              fill={primaryColor}\n              radius={[6, 6, 0, 0]}\n            />\n            <Bar\n              animationBegin={200}\n              animationDuration={800}\n              dataKey=\"secondary\"\n              fill={secondaryColor}\n              radius={[6, 6, 0, 0]}\n            />\n          </BarChart>\n        );\n      case \"line\":\n        return (\n          <LineChart {...commonProps}>\n            <CartesianGrid\n              stroke={gridColor}\n              strokeDasharray=\"3 3\"\n              vertical={false}\n            />\n            <XAxis dataKey=\"name\" {...axisProps} />\n            <YAxis {...axisProps} />\n            <Tooltip content={<ChartTooltip />} />\n            <Line\n              activeDot={{ r: 6 }}\n              animationDuration={1200}\n              dataKey=\"value\"\n              dot={{ fill: primaryColor, r: 4 }}\n              stroke={primaryColor}\n              strokeWidth={2.5}\n              type=\"monotone\"\n            />\n            <Line\n              activeDot={{ r: 6 }}\n              animationBegin={300}\n              animationDuration={1200}\n              dataKey=\"secondary\"\n              dot={{ fill: secondaryColor, r: 4 }}\n              stroke={secondaryColor}\n              strokeWidth={2.5}\n              type=\"monotone\"\n            />\n          </LineChart>\n        );\n      case \"area\":\n        return (\n          <AreaChart {...commonProps}>\n            <defs>\n              <linearGradient id=\"chartGradPrimary\" x1=\"0\" x2=\"0\" y1=\"0\" y2=\"1\">\n                <stop offset=\"0%\" stopColor={primaryColor} stopOpacity={0.3} />\n                <stop offset=\"95%\" stopColor={primaryColor} stopOpacity={0} />\n              </linearGradient>\n              <linearGradient\n                id=\"chartGradSecondary\"\n                x1=\"0\"\n                x2=\"0\"\n                y1=\"0\"\n                y2=\"1\"\n              >\n                <stop\n                  offset=\"0%\"\n                  stopColor={secondaryColor}\n                  stopOpacity={0.3}\n                />\n                <stop offset=\"95%\" stopColor={secondaryColor} stopOpacity={0} />\n              </linearGradient>\n            </defs>\n            <CartesianGrid\n              stroke={gridColor}\n              strokeDasharray=\"3 3\"\n              vertical={false}\n            />\n            <XAxis dataKey=\"name\" {...axisProps} />\n            <YAxis {...axisProps} />\n            <Tooltip content={<ChartTooltip />} />\n            <Area\n              animationDuration={1200}\n              dataKey=\"value\"\n              fill=\"url(#chartGradPrimary)\"\n              stroke={primaryColor}\n              strokeWidth={2}\n              type=\"monotone\"\n            />\n            <Area\n              animationBegin={300}\n              animationDuration={1200}\n              dataKey=\"secondary\"\n              fill=\"url(#chartGradSecondary)\"\n              stroke={secondaryColor}\n              strokeWidth={2}\n              type=\"monotone\"\n            />\n          </AreaChart>\n        );\n      default:\n        return (\n          <BarChart {...commonProps}>\n            <CartesianGrid\n              stroke={gridColor}\n              strokeDasharray=\"3 3\"\n              vertical={false}\n            />\n            <XAxis dataKey=\"name\" {...axisProps} />\n            <YAxis {...axisProps} />\n            <Tooltip content={<ChartTooltip />} />\n            <Bar\n              animationDuration={800}\n              dataKey=\"value\"\n              fill={primaryColor}\n              radius={[6, 6, 0, 0]}\n            />\n            <Bar\n              animationBegin={200}\n              animationDuration={800}\n              dataKey=\"secondary\"\n              fill={secondaryColor}\n              radius={[6, 6, 0, 0]}\n            />\n          </BarChart>\n        );\n    }\n  };\n\n  return (\n    <motion.div\n      animate={{ opacity: 1, y: 0 }}\n      className={cn(\n        \"rounded-xl border border-border bg-card p-6 shadow-sm\",\n        className\n      )}\n      initial={{ opacity: 0, y: 20 }}\n      transition={{ duration: 0.5, ease: [0.25, 0.1, 0.25, 1] }}\n    >\n      <div className=\"mb-6 flex items-start justify-between\">\n        <div>\n          <h3 className=\"font-semibold text-card-foreground text-lg\">\n            {title}\n          </h3>\n          <p className=\"mt-0.5 text-muted-foreground text-sm\">{description}</p>\n        </div>\n        <div className=\"relative flex h-8 items-center\">\n          <select\n            aria-label=\"Chart type\"\n            className={cn(\n              \"h-full min-w-22 appearance-none rounded-md border border-input bg-background pr-8 pl-3 font-medium text-foreground text-xs shadow-sm\",\n              \"focus-visible:outline-none focus-visible:ring-2 focus-visible:ring-ring\"\n            )}\n            onChange={(e) => setActiveChart(e.target.value as ChartType)}\n            value={activeChart}\n          >\n            {CHART_TYPE_OPTIONS.map((opt) => (\n              <option key={opt.type} value={opt.type}>\n                {opt.label}\n              </option>\n            ))}\n          </select>\n          <ChevronDown\n            aria-hidden\n            className=\"pointer-events-none absolute top-1/2 right-2.5 size-3.5 shrink-0 -translate-y-1/2 text-muted-foreground\"\n          />\n        </div>\n      </div>\n      <motion.div\n        animate={{ opacity: 1 }}\n        className=\"h-[280px] w-full\"\n        initial={{ opacity: 0 }}\n        key={activeChart}\n        transition={{ duration: 0.3 }}\n      >\n        <ResponsiveContainer height=\"100%\" width=\"100%\">\n          {renderChart()}\n        </ResponsiveContainer>\n      </motion.div>\n      <div className=\"mt-4 flex items-center gap-6 border-border border-t pt-4\">\n        <div className=\"flex items-center gap-2 text-muted-foreground text-xs\">\n          <span\n            className=\"h-2.5 w-2.5 rounded-full\"\n            style={{ backgroundColor: primaryColor }}\n          />\n          Primary\n        </div>\n        <div className=\"flex items-center gap-2 text-muted-foreground text-xs\">\n          <span\n            className=\"h-2.5 w-2.5 rounded-full\"\n            style={{ backgroundColor: secondaryColor }}\n          />\n          Secondary\n        </div>\n      </div>\n    </motion.div>\n  );\n}\n",
      "type": "registry:ui"
    }
  ],
  "title": "Chart",
  "description": "Animated Bar, Line, and Area chart with variant dropdown. Uses Recharts and Framer Motion. Colors defined in component."
}
